napari_workflow_inspector/__init__.py
napari_workflow_inspector/_dock_widget.py
napari_workflow_inspector/_tests/__init__.py
napari_workflow_inspector/_tests/test_dock_widget.py
napari_workflow_inspector-0.2.2.dist-info/LICENSE
napari_workflow_inspector-0.2.2.dist-info/METADATA
napari_workflow_inspector-0.2.2.dist-info/WHEEL
napari_workflow_inspector-0.2.2.dist-info/entry_points.txt
napari_workflow_inspector-0.2.2.dist-info/top_level.txt
napari_workflow_inspector-0.2.2.dist-info/RECORD
