Metadata-Version: 2.1
Name: napari-workflow-inspector
Version: 0.2.2
Summary: Inspect relationships between image processing operations in active workflows in napari
Home-page: https://github.com/haesleinhuepf/napari-workflow-inspector
Author: Robert Haase
Author-email: robert.haase@tu-dresden.de
License: BSD-3-Clause
Project-URL: Bug Tracker, https://github.com/haesleinhuepf/napari-workflow-inspector/issues
Project-URL: Documentation, https://github.com/haesleinhuepf/napari-workflow-inspector#README.md
Project-URL: Source Code, https://github.com/haesleinhuepf/napari-workflow-inspector
Project-URL: User Support, https://github.com/haesleinhuepf/napari-workflow-inspector/issues
Platform: UNKNOWN
Classifier: Development Status :: 3 - Alpha
Classifier: Intended Audience :: Developers
Classifier: Framework :: napari
Classifier: Topic :: Scientific/Engineering :: Image Processing
Classifier: Topic :: Scientific/Engineering :: Information Analysis
Classifier: Topic :: Scientific/Engineering :: Medical Science Apps.
Classifier: Programming Language :: Python
Classifier: Programming Language :: Python :: 3
Classifier: Programming Language :: Python :: 3.7
Classifier: Programming Language :: Python :: 3.8
Classifier: Programming Language :: Python :: 3.9
Classifier: Operating System :: OS Independent
Classifier: License :: OSI Approved :: BSD License
Requires-Python: >=3.7
License-File: LICENSE
Requires-Dist: napari-plugin-engine (>=0.1.4)
Requires-Dist: numpy
Requires-Dist: napari-tools-menu
Requires-Dist: networkx
Requires-Dist: matplotlib
Requires-Dist: napari-workflows
